doc_page_extractor/__init__.py
doc_page_extractor/clipper.py
doc_page_extractor/downloader.py
doc_page_extractor/extractor.py
doc_page_extractor/latex.py
doc_page_extractor/layout_order.py
doc_page_extractor/layoutreader.py
doc_page_extractor/models.py
doc_page_extractor/ocr.py
doc_page_extractor/ocr_corrector.py
doc_page_extractor/overlap.py
doc_page_extractor/plot.py
doc_page_extractor/raw_optimizer.py
doc_page_extractor/rectangle.py
doc_page_extractor/rotation.py
doc_page_extractor/table.py
doc_page_extractor/types.py
doc_page_extractor/utils.py
doc_page_extractor/onnxocr/__init__.py
doc_page_extractor/onnxocr/cls_postprocess.py
doc_page_extractor/onnxocr/db_postprocess.py
doc_page_extractor/onnxocr/imaug.py
doc_page_extractor/onnxocr/operators.py
doc_page_extractor/onnxocr/predict_base.py
doc_page_extractor/onnxocr/predict_cls.py
doc_page_extractor/onnxocr/predict_det.py
doc_page_extractor/onnxocr/predict_rec.py
doc_page_extractor/onnxocr/predict_system.py
doc_page_extractor/onnxocr/rec_postprocess.py
doc_page_extractor/onnxocr/utils.py
doc_page_extractor/struct_eqtable/__init__.py
doc_page_extractor/struct_eqtable/internvl/__init__.py
doc_page_extractor/struct_eqtable/internvl/conversation.py
doc_page_extractor/struct_eqtable/internvl/internvl.py
doc_page_extractor/struct_eqtable/internvl/internvl_lmdeploy.py
doc_page_extractor/struct_eqtable/pix2s/__init__.py
doc_page_extractor/struct_eqtable/pix2s/pix2s.py
doc_page_extractor/struct_eqtable/pix2s/pix2s_trt.py
doc_page_extractor_test/__init__.py
doc_page_extractor_test/clipper.py
doc_page_extractor_test/downloader.py
doc_page_extractor_test/extractor.py
doc_page_extractor_test/latex.py
doc_page_extractor_test/layout_order.py
doc_page_extractor_test/layoutreader.py
doc_page_extractor_test/models.py
doc_page_extractor_test/ocr.py
doc_page_extractor_test/ocr_corrector.py
doc_page_extractor_test/overlap.py
doc_page_extractor_test/plot.py
doc_page_extractor_test/raw_optimizer.py
doc_page_extractor_test/rectangle.py
doc_page_extractor_test-0.2.3.dist-info/LICENSE
doc_page_extractor_test-0.2.3.dist-info/METADATA
doc_page_extractor_test-0.2.3.dist-info/WHEEL
doc_page_extractor_test-0.2.3.dist-info/top_level.txt
doc_page_extractor_test-0.2.3.dist-info/RECORD
