Metadata-Version: 2.1
Name: doc-page-extractor-test
Version: 0.2.3
Summary: doc page extractor can identify text and format in images and return structured data.
Home-page: https://github.com/Moskize91/doc-page-extractor
Author: Tao Zeyu
Author-email: i@taozeyu.com
License-File: LICENSE
Requires-Dist: pillow<11.0,>=10.3
Requires-Dist: pyclipper<2.0,>=1.2.0
Requires-Dist: numpy<2.0,>=1.24.0
Requires-Dist: shapely<3.0,>=2.0.0
Requires-Dist: transformers<=4.47,>=4.42.4
Requires-Dist: doclayout-yolo>=0.0.3
Requires-Dist: pix2tex<=0.2.0,>=0.1.4
Requires-Dist: accelerate<2.0,>=1.6.0
Requires-Dist: huggingface-hub>=0.30.2
